MultiWii/__init__.py
MultiWii-0.0.1.dist-info/LICENSE
MultiWii-0.0.1.dist-info/METADATA
MultiWii-0.0.1.dist-info/WHEEL
MultiWii-0.0.1.dist-info/top_level.txt
MultiWii-0.0.1.dist-info/RECORD
