Metadata-Version: 2.1
Name: MultiWii
Version: 0.0.1
Summary: Python3 implementation of the Multi Serial Protocol
Home-page: https://github.com/PrrismStudios/MSP
Author: Yuma (Prrism)
Author-email: yumatezu@gmail.com
License: UNKNOWN
Platform: UNKNOWN
Classifier: Programming Language :: Python :: 3
Classifier: License :: OSI Approved :: MIT License
Classifier: Operating System :: OS Independent
Requires-Python: >=3.7
